[
{
"SectionId": "secn7943",
"Term1": "4.666666666666667",
"Term2": "5.25",
"Term3": "7.0"
},
{
"SectionId": "secn7944",
"Term1": "4.375",
"Term2": "5.375",
"Term3": "6.333333333333333"
},
{
"SectionId": "secn7945",
"Term1": "3.6153846153846154",
"Term2": "4.75",
"Term3": "6.333333333333333"
},
{
"SectionId": "secn7946",
"Term1": "4.833333333333333",
"Term2": "5.625",
"Term3": "6.0"
},
{
"SectionId": "secn7947",
"Term1": "4.428571428571429",
"Term2": "5.0",
"Term3": "5.7"
},
{
"SectionId": "secn7948",
"Term1": "3.5",
"Term2": "5.0",
"Term3": "6.0"
}
]