[
{
"SectionId": "secn33963",
"Term1": "3.0",
"Term2": "5.166666666666667",
"Term3": "5.16"
},
{
"SectionId": "secn33964",
"Term1": "3.4",
"Term2": "6.0",
"Term3": "5.1875"
},
{
"SectionId": "secn33965",
"Term1": "2.75",
"Term2": "5.0",
"Term3": "5.130434782608695"
},
{
"SectionId": "secn33966",
"Term1": "2.25",
"Term2": "6.4",
"Term3": "5.064516129032258"
},
{
"SectionId": "secn33967",
"Term1": "3.5714285714285716",
"Term2": "5.428571428571429",
"Term3": "5.0"
},
{
"SectionId": "secn33968",
"Term1": "2.0",
"Term2": "4.75",
"Term3": "5.064516129032258"
}
]