[
{
"SectionId": "secn22386",
"Term1": "2.0",
"Term2": "3.2",
"Term3": "7.166666666666667"
},
{
"SectionId": "secn22387",
"Term1": "3.2",
"Term2": "3.6666666666666665",
"Term3": "6.833333333333333"
},
{
"SectionId": "secn22388",
"Term1": "1.4",
"Term2": "3.5",
"Term3": "6.6"
},
{
"SectionId": "secn22389",
"Term1": "2.0",
"Term2": "4.6",
"Term3": "6.2727272727272725"
},
{
"SectionId": "secn22390",
"Term1": "2.25",
"Term2": "5.0",
"Term3": "6.444444444444445"
},
{
"SectionId": "secn22391",
"Term1": "1.6666666666666667",
"Term2": "3.6666666666666665",
"Term3": "7.1"
}
]