[
{
"SectionId": "secn33716",
"Term1": "4.333333333333333",
"Term2": "5.0",
"Term3": "5.057142857142857"
},
{
"SectionId": "secn33717",
"Term1": "2.875",
"Term2": "5.285714285714286",
"Term3": "5.0625"
},
{
"SectionId": "secn33718",
"Term1": "3.25",
"Term2": "6.333333333333333",
"Term3": "4.962962962962963"
},
{
"SectionId": "secn33719",
"Term1": "2.8",
"Term2": "5.1",
"Term3": "5.317073170731708"
},
{
"SectionId": "secn33720",
"Term1": "3.0",
"Term3": "5.333333333333333"
},
{
"SectionId": "secn33721",
"Term1": "3.25",
"Term2": "4.6",
"Term3": "5.0"
}
]