[
{
"SectionId": "secn22581",
"Term1": "2.4545454545454546",
"Term2": "3.4285714285714284",
"Term3": "6.666666666666667"
},
{
"SectionId": "secn22582",
"Term1": "4.0",
"Term2": "3.4",
"Term3": "7.0"
},
{
"SectionId": "secn22583",
"Term1": "1.3333333333333333",
"Term2": "4.5",
"Term3": "6.625"
},
{
"SectionId": "secn22584",
"Term1": "1.8",
"Term2": "3.25",
"Term3": "7.444444444444445"
},
{
"SectionId": "secn22585",
"Term1": "1.6",
"Term2": "3.4",
"Term3": "7.0"
},
{
"SectionId": "secn22586",
"Term1": "2.142857142857143",
"Term2": "3.8",
"Term3": "7.2"
}
]